freeman/__init__.py
freeman/auth/README.md
freeman/auth/__init__.py
freeman/auth/admin.py
freeman/auth/apps.py
freeman/auth/migrations/__init__.py
freeman/auth/models.py
freeman/auth/signals.py
freeman/auth/tests.py
freeman/auth/views.py
freeman/middlewares/errorhandling.py
freeman/middlewares/picking.py
freeman/models/abstract.py
freeman/models/types.py
freeman/settings.py
freeman/utils/dsa.py
freeman/utils/dto.py
freeman/utils/exceptions.py
freeman/utils/funcache.py
freeman/utils/models.py
freeman/utils/picking.py
freeman/utils/query.py
freeman/utils/strings.py
freeman/utils/typecheck.py
django_freeman-0.2.1.dist-info/LICENSE
django_freeman-0.2.1.dist-info/METADATA
django_freeman-0.2.1.dist-info/WHEEL
django_freeman-0.2.1.dist-info/RECORD
