Metadata-Version: 2.1
Name: django-freeman
Version: 0.2.1
Summary: Collections of functions and helpers that helps speed up development of your django project
License: MIT
Author: rubbiekelvin
Author-email: rubbiekelvinvoltsman@gmail.com
Requires-Python: >=3.10,<4.0
Classifier: License :: OSI Approved :: MIT License
Classifier: Programming Language :: Python :: 3
Classifier: Programming Language :: Python :: 3.10
Classifier: Programming Language :: Python :: 3.11
Requires-Dist: django (>=4.2,<5.0)
Requires-Dist: djangorestframework (>=3.14.0,<4.0.0)
Requires-Dist: markdown (>=3.4.3,<4.0.0)
